hidennsim/__init__.py
hidennsim/py.typed
hidennsim/server.cp313-win_amd64.pyd
hidennsim/server.py
hidennsim/tools/__init__.py
hidennsim/tools/add_jax.cp313-win_amd64.pyd
hidennsim/tools/add_jax.py
hidennsim/tools/csv_dimensions.cp313-win_amd64.pyd
hidennsim/tools/csv_dimensions.py
hidennsim/tools/multiply_jax.cp313-win_amd64.pyd
hidennsim/tools/multiply_jax.py
hidennsim/tools/subtract_jax.cp313-win_amd64.pyd
hidennsim/tools/subtract_jax.py
hidennsim/tools/train_data.cp313-win_amd64.pyd
hidennsim/tools/train_data.py
hidennsim/tools/config/config_ref.yaml
hidennsim/tools/pyinn/Interpolator.py
hidennsim/tools/pyinn/__init__.py
hidennsim/tools/pyinn/dataset_classification.py
hidennsim/tools/pyinn/dataset_regression.py
hidennsim/tools/pyinn/main.py
hidennsim/tools/pyinn/model.py
hidennsim/tools/pyinn/model_utils.py
hidennsim/tools/pyinn/plot.py
hidennsim/tools/pyinn/precision.py
hidennsim/tools/pyinn/train.py
hidennsim-1.1.12.dist-info/METADATA
hidennsim-1.1.12.dist-info/WHEEL
hidennsim-1.1.12.dist-info/entry_points.txt
hidennsim-1.1.12.dist-info/top_level.txt
hidennsim-1.1.12.dist-info/RECORD
