Metadata-Version: 2.4
Name: hidennsim
Version: 1.1.12
Summary: MCP server with JAX-based numerical tools
Home-page: https://github.com/yourusername/hidennsim
Author: HIDENNSIM Team
Author-email: HIDENNSIM Team <support@hidennsim.com>
License: MIT
Project-URL: Homepage, https://github.com/yourusername/hidennsim
Project-URL: Documentation, https://hidennsim.readthedocs.io
Project-URL: Issues, https://github.com/yourusername/hidennsim/issues
Keywords: mcp,jax,numerical,llm,claude
Requires-Python: >=3.10
Requires-Dist: mcp>=1.0.0
Requires-Dist: pandas>=2.0.0
Requires-Dist: pyyaml>=6.0.0
Requires-Dist: numpy>=1.24.0
Requires-Dist: matplotlib>=3.7.0
Requires-Dist: optax>=0.1.7
Provides-Extra: cpu
Requires-Dist: jax[cpu]>=0.4.20; extra == "cpu"
Provides-Extra: cuda
Requires-Dist: jax[cuda12]>=0.4.20; extra == "cuda"
Provides-Extra: dev
Requires-Dist: pytest>=7.0.0; extra == "dev"
Requires-Dist: pytest-asyncio>=0.21.0; extra == "dev"
Requires-Dist: black>=23.0.0; extra == "dev"
Requires-Dist: mypy>=1.0.0; extra == "dev"
Requires-Dist: cibuildwheel>=2.16.0; extra == "dev"
Dynamic: author
Dynamic: home-page
Dynamic: requires-python
